logging_ext2/__about__.py
logging_ext2/__init__.py
logging_ext2/handlers.py
logging_ext2/types.py
logging_ext2-0.3.0.dist-info/METADATA
logging_ext2-0.3.0.dist-info/WHEEL
logging_ext2-0.3.0.dist-info/licenses/LICENSE
logging_ext2-0.3.0.dist-info/RECORD
