Metadata-Version: 2.4
Name: logging-ext2
Version: 0.3.0
Summary: extend python logging library
Project-URL: Documentation, https://github.com/ramwin/logging-ext#readme
Project-URL: Issues, https://github.com/ramwin/logging-ext/issues
Project-URL: Source, https://github.com/ramwin/logging-ext
Author-email: Xiang Wang <ramwin@qq.com>
License-Expression: MIT
License-File: LICENSE
Classifier: Development Status :: 4 - Beta
Classifier: Programming Language :: Python
Classifier: Programming Language :: Python :: 3.8
Classifier: Programming Language :: Python :: 3.9
Classifier: Programming Language :: Python :: 3.10
Classifier: Programming Language :: Python :: 3.11
Classifier: Programming Language :: Python :: 3.12
Classifier: Programming Language :: Python :: Implementation :: CPython
Classifier: Programming Language :: Python :: Implementation :: PyPy
Requires-Python: >=3.8
Requires-Dist: filelock
